psemodel/__init__.py
psemodel/layers.py
psemodel/pap.py
psemodel/psedarknet.py
psemodel/pseresnet.py
psemodel/se.py
psemodel-0.1.3.dist-info/METADATA
psemodel-0.1.3.dist-info/WHEEL
psemodel-0.1.3.dist-info/top_level.txt
psemodel-0.1.3.dist-info/RECORD
