Metadata-Version: 2.1
Name: psemodel
Version: 0.1.3
Summary: A Position sequeeze and excitation model (resnet and darknet) for pytorch
Home-page: https://github.com/andrijdavid/Psemodel
Author: Andrij David
Author-email: david@geek.mg
License: UNKNOWN
Platform: UNKNOWN
Classifier: Programming Language :: Python :: 3
Classifier: License :: OSI Approved :: MIT License
Classifier: Operating System :: OS Independent
